generative_model_tools/__init__.py
generative_model_tools/write_images_in_html.py
generative_model_tools/write_images_in_html/__init__.py
generative_model_tools/write_images_in_html/write_images_in_html.py
generative_model_tools-0.1.dist-info/LICENSE
generative_model_tools-0.1.dist-info/METADATA
generative_model_tools-0.1.dist-info/WHEEL
generative_model_tools-0.1.dist-info/top_level.txt
generative_model_tools-0.1.dist-info/RECORD
